looper/__init__.py
looper/__main__.py
looper/_version.py
looper/cli_divvy.py
looper/cli_pydantic.py
looper/conductor.py
looper/const.py
looper/divvy.py
looper/exceptions.py
looper/looper.py
looper/parser_types.py
looper/pipeline_interface.py
looper/plugins.py
looper/processed_project.py
looper/project.py
looper/utils.py
looper/command_models/DEVELOPER.md
looper/command_models/README.md
looper/command_models/__init__.py
looper/command_models/arguments.py
looper/command_models/commands.py
looper/default_config/divvy_config.yaml
looper/default_config/divvy_templates/localhost_bulker_template.sub
looper/default_config/divvy_templates/localhost_docker_template.sub
looper/default_config/divvy_templates/localhost_singularity_template.sub
looper/default_config/divvy_templates/localhost_template.sub
looper/default_config/divvy_templates/lsf_template.sub
looper/default_config/divvy_templates/sge_template.sub
looper/default_config/divvy_templates/slurm_singularity_template.sub
looper/default_config/divvy_templates/slurm_template.sub
looper/jinja_templates/footer.html
looper/jinja_templates/footer_index.html
looper/jinja_templates/head.html
looper/jinja_templates/index.html
looper/jinja_templates/logo.html
looper/jinja_templates/navbar.html
looper/jinja_templates/navbar_links.html
looper/jinja_templates/navbar_list_parent.html
looper/jinja_templates/object.html
looper/jinja_templates/project_object.html
looper/jinja_templates/sample.html
looper/jinja_templates/status.html
looper/jinja_templates/status_table.html
looper/jinja_templates/status_table_no_links.html
looper/jinja_templates_old/footer.html
looper/jinja_templates_old/footer_index.html
looper/jinja_templates_old/head.html
looper/jinja_templates_old/index.html
looper/jinja_templates_old/logo.html
looper/jinja_templates_old/navbar.html
looper/jinja_templates_old/navbar_links.html
looper/jinja_templates_old/navbar_list_parent.html
looper/jinja_templates_old/object.html
looper/jinja_templates_old/project_object.html
looper-2.0.3.dist-info/licenses/LICENSE.txt
looper-2.0.3.dist-info/METADATA
looper-2.0.3.dist-info/WHEEL
looper-2.0.3.dist-info/entry_points.txt
looper-2.0.3.dist-info/top_level.txt
looper-2.0.3.dist-info/RECORD
