Metadata-Version: 2.4
Name: looper
Version: 2.0.3
Summary: A pipeline submission engine that parses sample inputs and submits pipelines for each sample.
Home-page: https://github.com/pepkit/looper
Author: Nathan Sheffield, Vince Reuter, Michal Stolarczyk, Johanna Klughammer, Andre Rendeiro
License: BSD2
Keywords: bioinformatics,sequencing,ngs
Classifier: Development Status :: 4 - Beta
Classifier: License :: OSI Approved :: BSD License
Classifier: Programming Language :: Python :: 3.8
Classifier: Programming Language :: Python :: 3.9
Classifier: Programming Language :: Python :: 3.10
Classifier: Programming Language :: Python :: 3.11
Classifier: Topic :: Scientific/Engineering :: Bio-Informatics
License-File: LICENSE.txt
Requires-Dist: colorama>=0.3.9
Requires-Dist: eido>=0.2.4
Requires-Dist: jinja2
Requires-Dist: logmuse>=0.2.0
Requires-Dist: pandas>=2.0.2
Requires-Dist: pephubclient>=0.4.0
Requires-Dist: pipestat>=0.12.0a1
Requires-Dist: peppy>=0.40.6
Requires-Dist: pyyaml>=3.12
Requires-Dist: rich>=9.10.0
Requires-Dist: ubiquerg>=0.8.1
Requires-Dist: yacman==0.9.3
Requires-Dist: pydantic-argparse>=0.9.0
Requires-Dist: psutil
Dynamic: author
Dynamic: classifier
Dynamic: description
Dynamic: description-content-type
Dynamic: home-page
Dynamic: keywords
Dynamic: license
Dynamic: license-file
Dynamic: requires-dist
Dynamic: summary
